mesh_to_sdf/__init__.py
mesh_to_sdf/pyrender_wrapper.py
mesh_to_sdf/scan.py
mesh_to_sdf/surface_point_cloud.py
mesh_to_sdf/utils.py
mesh_to_sdf/shaders/mesh.frag
mesh_to_sdf/shaders/mesh.vert
mesh_to_sdf-0.0.15.data/data/shaders/mesh.frag
mesh_to_sdf-0.0.15.data/data/shaders/mesh.vert
mesh_to_sdf-0.0.15.dist-info/LICENSE
mesh_to_sdf-0.0.15.dist-info/METADATA
mesh_to_sdf-0.0.15.dist-info/WHEEL
mesh_to_sdf-0.0.15.dist-info/top_level.txt
mesh_to_sdf-0.0.15.dist-info/RECORD
