Metadata-Version: 2.1
Name: mesh-to-sdf
Version: 0.0.15
Summary: Calculate signed distance fields for arbitrary meshes
Home-page: https://github.com/marian42/mesh_to_sdf
Author: Marian Kleineberg
Author-email: mail@marian42.de
License: UNKNOWN
Platform: UNKNOWN
Classifier: Programming Language :: Python :: 3
Classifier: License :: OSI Approved :: MIT License
Classifier: Operating System :: OS Independent
Requires-Python: >=3.5
License-File: LICENSE
Requires-Dist: pyopengl
Requires-Dist: pyrender
Requires-Dist: scikit-image
Requires-Dist: scikit-learn
